pyvolgrid/__init__.py
pyvolgrid/_core.cpython-312-x86_64-linux-gnu.so
pyvolgrid/_core.pyi
pyvolgrid-0.1.2.dist-info/METADATA
pyvolgrid-0.1.2.dist-info/WHEEL
pyvolgrid-0.1.2.dist-info/RECORD
pyvolgrid-0.1.2.dist-info/licenses/LICENSE.txt
