Metadata-Version: 2.1
Name: pyvolgrid
Version: 0.1.2
Summary: Python package for estimating the total volume of overlapping spheres using a grid-based numerical approach.
Keywords: molecular modeling,structural bioinformatics,computational chemistry,volume calculation,grid-based methods
Author-Email: Karl Gruber <gammaturn@gmail.com>
Maintainer-Email: Karl Gruber <gammaturn@gmail.com>
License: MIT
Classifier: Programming Language :: Python :: 3
Classifier: Programming Language :: Python :: 3.11
Classifier: Programming Language :: Python :: 3.12
Classifier: Programming Language :: Python :: 3.13
Classifier: Programming Language :: Python :: 3.14
Classifier: License :: OSI Approved :: MIT License
Classifier: Operating System :: OS Independent
Project-URL: Homepage, https://github.com/ugSUBMARINE/pyvolgrid
Project-URL: Documentation, https://github.com/ugSUBMARINE/pyvolgrid#readme
Project-URL: Repository, https://github.com/ugSUBMARINE/pyvolgrid.git
Project-URL: Bug Tracker, https://github.com/ugSUBMARINE/pyvolgrid/issues
Project-URL: Changelog, https://github.com/ugSUBMARINE/pyvolgrid/releases
Requires-Python: >=3.11
Requires-Dist: numpy>=1.26
